carbonfootprint/NamedLists.py
carbonfootprint/__init__.py
carbonfootprint/carbon.py
carbonfootprint/fuelmix.py
carbonfootprint/dataset/carbon4.csv
carbonfootprint/dataset/caiso2020/930-data-export-01.csv
carbonfootprint/dataset/caiso2020/930-data-export-02.csv
carbonfootprint/dataset/caiso2020/930-data-export-03.csv
carbonfootprint/dataset/caiso2020/930-data-export-04.csv
carbonfootprint/dataset/caiso2020/930-data-export-05.csv
carbonfootprint/dataset/caiso2020/930-data-export-06.csv
carbonfootprint/dataset/caiso2020/930-data-export-07.csv
carbonfootprint/dataset/caiso2020/930-data-export-08.csv
carbonfootprint/dataset/caiso2020/930-data-export-09.csv
carbonfootprint/dataset/caiso2020/930-data-export-10.csv
carbonfootprint/dataset/caiso2020/930-data-export-11.csv
carbonfootprint/dataset/caiso2020/930-data-export-12.csv
carbonfootprint/dataset/isone2020/930-data-export-01.csv
carbonfootprint/dataset/isone2020/930-data-export-02.csv
carbonfootprint/dataset/isone2020/930-data-export-03.csv
carbonfootprint/dataset/isone2020/930-data-export-04.csv
carbonfootprint/dataset/isone2020/930-data-export-05.csv
carbonfootprint/dataset/isone2020/930-data-export-06.csv
carbonfootprint/dataset/isone2020/930-data-export-07.csv
carbonfootprint/dataset/isone2020/930-data-export-08.csv
carbonfootprint/dataset/isone2020/930-data-export-09.csv
carbonfootprint/dataset/isone2020/930-data-export-10.csv
carbonfootprint/dataset/isone2020/930-data-export-11.csv
carbonfootprint/dataset/isone2020/930-data-export-12.csv
carbonfootprint/dataset/north_west2020/930-data-export-01.csv
carbonfootprint/dataset/north_west2020/930-data-export-02.csv
carbonfootprint/dataset/north_west2020/930-data-export-03.csv
carbonfootprint/dataset/north_west2020/930-data-export-04.csv
carbonfootprint/dataset/north_west2020/930-data-export-05.csv
carbonfootprint/dataset/north_west2020/930-data-export-06.csv
carbonfootprint/dataset/north_west2020/930-data-export-07.csv
carbonfootprint-1.2.4.dist-info/LICENSE
carbonfootprint-1.2.4.dist-info/METADATA
carbonfootprint-1.2.4.dist-info/WHEEL
carbonfootprint-1.2.4.dist-info/top_level.txt
carbonfootprint-1.2.4.dist-info/RECORD
