Metadata-Version: 2.1
Name: carbonfootprint
Version: 1.2.4
Summary: carbon footprint of the power consumption by fuel mix. Calculates carbon footprint based on fuel mix and discharge profile at the utility selected. Can create graphs and tabular output for fuel mix based on input file of series of power drawn over a period of time.
Home-page: https://github.com/renewable-energy-experiments/carbon-footprint-calculator
Author: Altanai
Author-email: tara181989@gmail.com
License: UNKNOWN
Project-URL: Bug Tracker, https://github.com/renewable-energy-experiments/carbon-footprint-calculator/issues
Keywords: carbon-emission,energy-efficiency,utility-fuel-mix
Platform: UNKNOWN
Classifier: Programming Language :: Python :: 3
Classifier: License :: OSI Approved :: GNU General Public License (GPL)
Classifier: Operating System :: OS Independent
Classifier: Intended Audience :: Developers
Classifier: Intended Audience :: Education
Classifier: Intended Audience :: Science/Research
Requires-Python: >=3.6
License-File: LICENSE
Requires-Dist: pandas
